nbhistory/__init__.py
nbhistory/_nbdev.py
nbhistory/core.py
nbhistory-0.0.4.dist-info/LICENSE
nbhistory-0.0.4.dist-info/METADATA
nbhistory-0.0.4.dist-info/WHEEL
nbhistory-0.0.4.dist-info/entry_points.txt
nbhistory-0.0.4.dist-info/top_level.txt
nbhistory-0.0.4.dist-info/RECORD
